beginnerpy/__init__.py
beginnerpy/challenges/__init__.py
beginnerpy/challenges/adventure_game/game.py
beginnerpy/challenges/adventure_game/game_builder.py
beginnerpy/challenges/adventure_game/solution.py
beginnerpy/challenges/adventure_game/tests.py
beginnerpy/challenges/daily/c10.py
beginnerpy/challenges/daily/c11.py
beginnerpy/challenges/daily/c12.py
beginnerpy/challenges/daily/c13_longest_run.py
beginnerpy/challenges/daily/c14_work_buckets.py
beginnerpy/challenges/daily/c15_increasing_decreasing.py
beginnerpy/challenges/daily/c16_boom.py
beginnerpy/challenges/daily/c17_antipodes_average.py
beginnerpy/challenges/daily/c18_stretched_words.py
beginnerpy/challenges/daily/c19_combinations.py
beginnerpy/challenges/daily/c2.py
beginnerpy/challenges/daily/c20_groceries.py
beginnerpy/challenges/daily/c21_first_before_second.py
beginnerpy/challenges/daily/c22_upvote.py
beginnerpy/challenges/daily/c23_calculator.py
beginnerpy/challenges/daily/c24_remove_extras.py
beginnerpy/challenges/daily/c25_directonally_challenged.py
beginnerpy/challenges/daily/c26_bigrams.py
beginnerpy/challenges/daily/c27_shift_validators.py
beginnerpy/challenges/daily/c28_potions.py
beginnerpy/challenges/daily/c29_swimming_pools.py
beginnerpy/challenges/daily/c3.py
beginnerpy/challenges/daily/c30_reverse_coding.py
beginnerpy/challenges/daily/c31_mini_peaks.py
beginnerpy/challenges/daily/c32_compass_directions.py
beginnerpy/challenges/daily/c33_union_intersection.py
beginnerpy/challenges/daily/c34_intersecting_intervals.py
beginnerpy/challenges/daily/c35_round_to_n.py
beginnerpy/challenges/daily/c36_pizza_points.py
beginnerpy/challenges/daily/c37_match_last.py
beginnerpy/challenges/daily/c38_rearrange_number.py
beginnerpy/challenges/daily/c39_left_most_digit.py
beginnerpy/challenges/daily/c4.py
beginnerpy/challenges/daily/c40_sum_of_nth.py
beginnerpy/challenges/daily/c41_matrix_movement.py
beginnerpy/challenges/daily/c41_matrix_movement_oop.py
beginnerpy/challenges/daily/c42_factorial.py
beginnerpy-2020.2.4.dist-info/WHEEL
beginnerpy-2020.2.4.dist-info/METADATA
beginnerpy-2020.2.4.dist-info/RECORD
