Metadata-Version: 2.1
Name: beginnerpy
Version: 2020.2.4
Summary: 
Author: Zech Zimmerman
Author-email: hi@beginnerpy.com
Requires-Python: >=3.7.0,<4.0.0
Classifier: Programming Language :: Python :: 3
Classifier: Programming Language :: Python :: 3.7
Classifier: Programming Language :: Python :: 3.8
Requires-Dist: colorama (>=0.4.3,<0.5.0)
Requires-Dist: toml (>=0.10.1,<0.11.0)
